packgithub/__init__.py
packgithub/checkuser.py
packgithub/clear_clean_repo.py
packgithub/clone.py
packgithub/create.py
packgithub/delete.py
packgithub-0.0.1.dist-info/LICENCE.txt
packgithub-0.0.1.dist-info/METADATA
packgithub-0.0.1.dist-info/WHEEL
packgithub-0.0.1.dist-info/top_level.txt
packgithub-0.0.1.dist-info/RECORD
