Metadata-Version: 2.1
Name: packgithub
Version: 0.0.1
Summary: Github automation using python
Home-page: UNKNOWN
Author: Anukrati Rawal
Author-email: anukratirawal1.4@gmail.com
License: MIT
Platform: UNKNOWN
Requires-Dist: GitPython (==3.1.11)
Requires-Dist: pypi (==2.1)
Requires-Dist: requests (==2.0.0)
